compas_view2/__init__.py
compas_view2/gl.py
compas_view2/app/__init__.py
compas_view2/app/app.py
compas_view2/app/config_default.json
compas_view2/app/controller.py
compas_view2/app/plot.py
compas_view2/app/selector.py
compas_view2/app/timer.py
compas_view2/app/worker.py
compas_view2/collections/__init__.py
compas_view2/collections/collection.py
compas_view2/flow/__init__.py
compas_view2/flow/flow.py
compas_view2/flow/node.py
compas_view2/flow/values.py
compas_view2/flow/widgets.py
compas_view2/fonts/FreeSans.ttf
compas_view2/forms/__init__.py
compas_view2/forms/addform.py
compas_view2/forms/collapsiblebox.py
compas_view2/forms/dockform.py
compas_view2/forms/form.py
compas_view2/forms/line.py
compas_view2/forms/objects.py
compas_view2/forms/point.py
compas_view2/forms/pointedit.py
compas_view2/forms/propertyform.py
compas_view2/forms/sceneform.py
compas_view2/forms/sphere.py
compas_view2/forms/tabsform.py
compas_view2/forms/torus.py
compas_view2/forms/treeform.py
compas_view2/icons/compas_icon_white.png
compas_view2/objects/__init__.py
compas_view2/objects/arrowobject.py
compas_view2/objects/boxobject.py
compas_view2/objects/brepobject.py
compas_view2/objects/bufferobject.py
compas_view2/objects/capsuleobject.py
compas_view2/objects/circleobject.py
compas_view2/objects/collectionobject.py
compas_view2/objects/compositeobject.py
compas_view2/objects/coneobject.py
compas_view2/objects/cylinderobject.py
compas_view2/objects/ellipseobject.py
compas_view2/objects/frameobject.py
compas_view2/objects/gridobject.py
compas_view2/objects/lineobject.py
compas_view2/objects/meshobject.py
compas_view2/objects/networkobject.py
compas_view2/objects/nurbssurfaceobject.py
compas_view2/objects/object.py
compas_view2/objects/planeobject.py
compas_view2/objects/pointcloudobject.py
compas_view2/objects/pointobject.py
compas_view2/objects/polygonobject.py
compas_view2/objects/polyhedronobject.py
compas_view2/objects/polylineobject.py
compas_view2/objects/robotobject.py
compas_view2-0.11.0.dist-info/AUTHORS.md
compas_view2-0.11.0.dist-info/LICENSE
compas_view2-0.11.0.dist-info/METADATA
compas_view2-0.11.0.dist-info/WHEEL
compas_view2-0.11.0.dist-info/top_level.txt
compas_view2-0.11.0.dist-info/RECORD
